{
    "children": [
        {
            "id": 0,
            "is_logic_active": false,
            "is_physic_active": true,
            "is_visible": true,
            "layer": "Default",
            "model.id": 28,
            "name": "licznik",
            "no_textures": false,
            "position": {
                "x": -12.0,
                "y": 0.0,
                "z": 0.0
            },
            "rotation": {
                "w": 1.0,
                "x": 0.0,
                "y": 0.0,
                "z": 0.0
            },
            "scale": {
                "x": 1.0,
                "y": 1.0,
                "z": 1.0
            },
            "tag": "Default",
            "type": "Node"
        },
        {
            "id": 0,
            "is_logic_active": false,
            "is_physic_active": true,
            "is_visible": true,
            "layer": "Default",
            "model.id": 26,
            "name": "Prosta",
            "no_textures": false,
            "position": {
                "x": -6.0,
                "y": 0.0,
                "z": 0.0
            },
            "rotation": {
                "w": 1.0,
                "x": 0.0,
                "y": 0.0,
                "z": 0.0
            },
            "scale": {
                "x": 1.0,
                "y": 1.0,
                "z": 1.0
            },
            "tag": "Default",
            "type": "Node"
        },
        {
            "id": 0,
            "is_logic_active": false,
            "is_physic_active": true,
            "is_visible": true,
            "layer": "Default",
            "model.id": 27,
            "name": "rura_zakret",
            "no_textures": false,
            "position": {
                "x": 0.0,
                "y": 0.0,
                "z": 0.0
            },
            "rotation": {
                "w": -0.00030532656819559634,
                "x": 4.372957462805971e-08,
                "y": 0.9999999403953552,
                "z": -4.370009065723934e-08
            },
            "scale": {
                "x": 1.0,
                "y": 1.0,
                "z": 1.0
            },
            "tag": "Default",
            "type": "Node"
        },
        {
            "id": 0,
            "is_logic_active": false,
            "is_physic_active": true,
            "is_visible": true,
            "layer": "Default",
            "model.id": 29,
            "name": "t",
            "no_textures": false,
            "position": {
                "x": -12.0,
                "y": -6.0,
                "z": 0.0
            },
            "rotation": {
                "w": 1.0,
                "x": 0.0,
                "y": 0.0,
                "z": 0.0
            },
            "scale": {
                "x": 1.0,
                "y": 1.0,
                "z": 1.0
            },
            "tag": "Default",
            "type": "Node"
        },
        {
            "id": 0,
            "is_logic_active": false,
            "is_physic_active": true,
            "is_visible": true,
            "layer": "Default",
            "model.id": 33,
            "name": "valve",
            "no_textures": false,
            "position": {
                "x": -6.0,
                "y": -6.0,
                "z": 0.0
            },
            "rotation": {
                "w": 1.0,
                "x": 0.0,
                "y": 0.0,
                "z": 0.0
            },
            "scale": {
                "x": 1.0,
                "y": 1.0,
                "z": 1.0
            },
            "tag": "Default",
            "type": "Node"
        },
        {
            "id": 0,
            "is_logic_active": false,
            "is_physic_active": true,
            "is_visible": true,
            "layer": "Default",
            "model.id": 32,
            "name": "x",
            "no_textures": false,
            "position": {
                "x": 0.0,
                "y": -6.0,
                "z": 0.0
            },
            "rotation": {
                "w": 1.0,
                "x": 0.0,
                "y": 0.0,
                "z": 0.0
            },
            "scale": {
                "x": 1.0,
                "y": 1.0,
                "z": 1.0
            },
            "tag": "Default",
            "type": "Node"
        }
    ],
    "id": 0,
    "is_logic_active": false,
    "is_physic_active": true,
    "is_visible": true,
    "layer": "Default",
    "model.id": -1,
    "name": "pipes",
    "no_textures": true,
    "position": {
        "x": 0.0,
        "y": 0.0,
        "z": 0.0
    },
    "rotation": {
        "w": 1.0,
        "x": 0.0,
        "y": 0.0,
        "z": 0.0
    },
    "scale": {
        "x": 1.0,
        "y": 1.0,
        "z": 1.0
    },
    "tag": "Default",
    "type": "Node"
}